[{"name":"lZ7x8J","marks":78},{"name":"G9JO","marks":79},{"name":"soHo6","marks":86},{"name":"GjTpZkN","marks":30},{"name":"oO","marks":48},{"name":"Z0ygGqiMl","marks":51},{"name":"Dx8smQJBq","marks":41},{"name":"D4OksXJg","marks":23},{"name":"gUREuHY","marks":59},{"name":"ar5ME","marks":68},{"name":"aeQ6i0j3","marks":0},{"name":"4BBaXT","marks":60},{"name":"NJU8","marks":4},{"name":"Xg740","marks":51},{"name":"NK8Rs","marks":66},{"name":"JmYtIv","marks":46},{"name":"Ps","marks":27},{"name":"oTYFy6","marks":59},{"name":"RIzktM","marks":69},{"name":"OH","marks":46},{"name":"wZwMtW","marks":42},{"name":"QWuTSaQ","marks":36},{"name":"OenZC","marks":13},{"name":"2fi","marks":51},{"name":"rt","marks":60},{"name":"XL0tUxiD","marks":80},{"name":"74","marks":14},{"name":"FDZG","marks":31},{"name":"XC0mVa69F","marks":40},{"name":"Vvk","marks":74},{"name":"wm2kmW","marks":0},{"name":"8VV","marks":70},{"name":"Ei","marks":54},{"name":"0BbALRXcw","marks":59},{"name":"9biiypj6","marks":64},{"name":"36X9LJ5tcI","marks":97},{"name":"8182vXyo5b","marks":2},{"name":"mgGsn","marks":57},{"name":"fCaF3nf2H","marks":22},{"name":"NHy","marks":94},{"name":"Z9KOQCh6W","marks":57},{"name":"oxFO7xW","marks":24},{"name":"5gY0","marks":29},{"name":"vHxA","marks":94},{"name":"QivCK","marks":72},{"name":"FaPXx","marks":88},{"name":"4srIfx","marks":75},{"name":"Ttl","marks":16},{"name":"OzJJgJJXQ7","marks":73},{"name":"1sm","marks":51},{"name":"ua49wwH3","marks":99},{"name":"5UFtuBfC0","marks":89},{"name":"F1z0qI","marks":99},{"name":"HN1k50U","marks":92},{"name":"nPlSkoeedi","marks":5},{"name":"gDvmAtdg","marks":95},{"name":"Y","marks":4},{"name":"5hPz0hq","marks":0},{"name":"8xByFaP","marks":72},{"name":"u7tRA5lD","marks":84},{"name":"0d9HX","marks":78},{"name":"ggSjtH","marks":58},{"name":"qA","marks":70},{"name":"vbWajtBUg","marks":65},{"name":"6Y89QeGZZ","marks":22},{"name":"dhF","marks":91},{"name":"mTvFDjFJP","marks":97},{"name":"mOZqtXb4c","marks":63},{"name":"akW1p","marks":22},{"name":"TQVpsj","marks":47},{"name":"Za","marks":65},{"name":"2gXAC4aI","marks":22},{"name":"XjnR","marks":92},{"name":"j9","marks":38},{"name":"v8EBEY","marks":55},{"name":"DKlTRuMNwL","marks":98},{"name":"lY7mfLhIo9","marks":56},{"name":"KbYusi","marks":2},{"name":"8","marks":68},{"name":"jxhMjxF","marks":72},{"name":"qAOn","marks":11},{"name":"Hk","marks":58},{"name":"AO8kTA1","marks":74},{"name":"YHS1","marks":19},{"name":"ZgiUzgVXZW","marks":48},{"name":"luLF","marks":85},{"name":"IVJRr","marks":32},{"name":"rA","marks":86},{"name":"C","marks":89},{"name":"FsLsmbC","marks":90},{"name":"H5","marks":27},{"name":"519oFt9Bc","marks":16},{"name":"0JgO4r9","marks":15},{"name":"sdA1PFSr7","marks":59},{"name":"q54Q","marks":92},{"name":"eK35IVD","marks":58},{"name":"k","marks":54},{"name":"oCxRVdiS1","marks":42},{"name":"Gtw","marks":76},{"name":"3e","marks":17}]